[
  {
    "url": "http://app10.com/detail.php?item_id=13/1/4/1", 
    "action": "http://app10.com/cart.php", 
    "parameter": {
      "qty[]": "1", 
      "prod_opt_12": "abcdefgh", 
      "cmd": "add", 
      "item_id[0]": "13", 
      "AXSRF_token": "", 
      "qty[0]": "abcdefgh"
    }, 
    "method": "post"
  }, 
  {
    "url": "http://app10.com/contact.php?", 
    "action": "http://app10.com/contact.php", 
    "parameter": {
      "name": "abcdefgh", 
      "cmd": "send", 
      "visual": "abcdefgh", 
      "AXSRF_token": "", 
      "email": "ex@amp.le", 
      "subject": "abcdefgh"
    }, 
    "method": "post"
  }, 
  {
    "url": "http://app10.com/tell.php?item_id=13", 
    "action": "http://app10.com/tell.php", 
    "parameter": {
      "name": "abcdefgh", 
      "friend_name": "abcdefgh", 
      "cmd": "send", 
      "contact_us": "0", 
      "friend_email": "abcdefgh", 
      "visual": "abcdefgh", 
      "item_id": "13", 
      "AXSRF_token": "", 
      "email": "abcdefgh"
    }, 
    "method": "post"
  }
]